[
  {
    "Apply": {
      "ViewBox": {
        "minx": {
          "Constant": 0.0
        },
        "miny": {
          "Constant": 0.0
        },
        "width": {
          "Constant": 1000.0
        },
        "height": {
          "Constant": 300.0
        }
      }
    }
  },
  {
    "Container": {
      "Canvas": {
        "width": {
          "Constant": {
            "cm": 10.0
          }
        },
        "height": {
          "Constant": {
            "cm": 3.0
          }
        }
      }
    }
  },
  {
    "Apply": {
      "Font": {
        "family": {
          "Constant": [
            {
              "Generic": "Verdana"
            }
          ]
        },
        "size": {
          "Constant": {
            "px": 55.0
          }
        }
      }
    }
  },
  {
    "Apply": {
      "Fill": {
        "paint": {
          "Constant": {
            "Color": [
              0,
              0,
              255
            ]
          }
        }
      }
    }
  },
  {
    "Container": {
      "Text": {
        "x": {
          "Constant": [
            {
              "px": 250.0
            }
          ]
        },
        "y": {
          "Constant": [
            {
              "px": 150.0
            }
          ]
        }
      }
    }
  },
  {
    "Draw": {
      "Characters": "Hello, out there"
    }
  },
  "Pop",
  {
    "Apply": {
      "Fill": {}
    }
  },
  {
    "Apply": {
      "Stroke": {
        "paint": {
          "Constant": {
            "Color": [
              0,
              0,
              255
            ]
          }
        },
        "width": {
          "Constant": {
            "px": 2.0
          }
        }
      }
    }
  },
  {
    "Draw": {
      "Rect": {
        "x": {
          "Constant": {
            "px": 1.0
          }
        },
        "y": {
          "Constant": {
            "px": 1.0
          }
        },
        "width": {
          "Constant": {
            "px": 998.0
          }
        },
        "height": {
          "Constant": {
            "px": 298.0
          }
        }
      }
    }
  },
  "Pop"
]